kubev2v/__init__.py
kubev2v/kubectl_mtv_server.py
kubev2v/kubectl_mtv_write_server.py
kubev2v/kubevirt_server.py
mtv_mcp-1.0.17.dist-info/METADATA
mtv_mcp-1.0.17.dist-info/WHEEL
mtv_mcp-1.0.17.dist-info/entry_points.txt
mtv_mcp-1.0.17.dist-info/top_level.txt
mtv_mcp-1.0.17.dist-info/RECORD
